.DS_Store
compnotes/__init__.py
compnotes/main.py
compnotes/h2comp/BST.py
compnotes/h2comp/CLDLL.py
compnotes/h2comp/DLLL.py
compnotes/h2comp/HT.py
compnotes/h2comp/SLLL.py
compnotes/h2comp/bSearch.py
compnotes/h2comp/inplace&iterQuickSort.py
compnotes/h2comp/k2d&d2k.py
compnotes/h2comp/lSearch.py
compnotes/h2comp/queue.py
compnotes/h2comp/sorting.py
compnotes/h2comp/stack.py
compnotes-0.0.5.dist-info/LICENSE
compnotes-0.0.5.dist-info/METADATA
compnotes-0.0.5.dist-info/WHEEL
compnotes-0.0.5.dist-info/top_level.txt
compnotes-0.0.5.dist-info/RECORD
