Metadata-Version: 2.1
Name: compnotes
Version: 0.0.5
Summary: notes in a package
Home-page: https://github.com/seelengxd/compnotes
Author: seelengxd
Author-email: seeleng200212@gmail.com
License: UNKNOWN
Platform: UNKNOWN
Classifier: Programming Language :: Python :: 3
Classifier: License :: OSI Approved :: MIT License
Classifier: Operating System :: OS Independent
Requires-Python: >=3.6
